<?xml version="1.0" encoding="windows-1256" ?>
<formulas>
	<formula c1="Ì" c2="Ë" c3="ã" noc="1" form1="A" form2="">
	</formula>
	<formula c1="Ì" c2="Í" c3="Ñ" noc="3" form1="A" form2="">
	</formula>
	<formula c1="Ì" c2="Ñ" c3="Ï" noc="1" form1="A" form2="">
	</formula>
	<formula c1="Ì" c2="Ñ" c3="Ñ" noc="1" form1="C" form2="">
	</formula>
	<formula c1="Ì" c2="Ò" c3="Ñ" noc="2" form1="B" form2="C">
	</formula>
	<formula c1="Ì" c2="Ó" c3="Ó" noc="1" form1="A" form2="C">
	</formula>
	<formula c1="Ì" c2="á" c3="Ó" noc="2" form1="B" form2="">
	</formula>
	<formula c1="Ì" c2="ã" c3="Ú" noc="3" form1="A" form2="C">
	</formula>
	<formula c1="Ì" c2="ã" c3="ã" noc="1" form1="A" form2="">
	</formula>
	<formula c1="Ì" c2="ä" c3="È" noc="1" form1="A" form2="">
	</formula>
	<formula c1="Ì" c2="ä" c3="ä" noc="1" form1="C" form2="">
	</formula>
	<formula c1="Ì" c2="æ" c3="Ò" noc="1" form1="A" form2="">
	</formula>
	<formula c1="Ì" c2="æ" c3="á" noc="1" form1="A" form2="">
	</formula>
</formulas>
