<?xml version="1.0" encoding="windows-1256" ?>
<roots>
	<root c1="Ö" c2="Ì" c3="Í" c4="Ñ">
		<augmentationFormula formulaNo="3" transitive="á" />
	</root>
	<root c1="Ö" c2="Í" c3="Ö" c4="Í">
		<augmentationFormula formulaNo="1" transitive="á" />
	</root>
	<root c1="Ö" c2="Ñ" c3="Û" c4="Ø">
		<augmentationFormula formulaNo="3" transitive="á" />
	</root>
	<root c1="Ö" c2="Ñ" c3="Û" c4="ã">
		<augmentationFormula formulaNo="1" transitive="á" />
	</root>
	<root c1="Ö" c2="Ñ" c3="Ý" c4="Ø">
		<augmentationFormula formulaNo="1" transitive="á" />
	</root>
	<root c1="Ö" c2="Ñ" c3="å" c4="Ò">
		<augmentationFormula formulaNo="3" transitive="á" />
	</root>
	<root c1="Ö" c2="Ú" c3="Ö" c4="Ú">
		<augmentationFormula formulaNo="1" transitive="á" />
	</root>
	<root c1="Ö" c2="Ý" c3="Á" c4="Ï">
		<augmentationFormula formulaNo="3" transitive="á" />
	</root>
	<root c1="Ö" c2="ß" c3="Ö" c4="ß">
		<augmentationFormula formulaNo="1" transitive="á" />
	</root>
	<root c1="Ö" c2="ã" c3="Á" c4="ß">
		<augmentationFormula formulaNo="3" transitive="á" />
	</root>
	<root c1="Ö" c2="ã" c3="Í" c4="á">
		<augmentationFormula formulaNo="3" transitive="á" />
	</root>
	<root c1="Ö" c2="ã" c3="Í" c4="ä">
		<augmentationFormula formulaNo="3" transitive="á" />
	</root>
	<root c1="Ö" c2="æ" c3="ß" c4="Ú">
		<augmentationFormula formulaNo="1" transitive="á" />
	</root>
	<root c1="Ö" c2="í" c3="Ò" c4="ä">
		<augmentationFormula formulaNo="1" transitive="á" />
	</root>
</roots>
