<?xml version="1.0" encoding="UTF-8" ?>
<formulas>
	<formula c1="ع" c2="ت" c3="ق">
	</formula>
	<formula c1="ع" c2="ج" c3="ب">
	</formula>
	<formula c1="ع" c2="د" c3="ل">
	</formula>
	<formula c1="ع" c2="ر" c3="ض">
	</formula>
	<formula c1="ع" c2="ز" c3="ز">
	</formula>
	<formula c1="ع" c2="س" c3="ر">
	</formula>
	<formula c1="ع" c2="ظ" c3="م">
	</formula>
	<formula c1="ع" c2="ق" c3="ل">
	</formula>
	<formula c1="ع" c2="ل" c3="م">
	</formula>
	<formula c1="ع" c2="ل" c3="و">
	</formula>
	<formula c1="ع" c2="م" c3="ق">
	</formula>
	<formula c1="ع" c2="ن" c3="ف">
	</formula>
</formulas>
