<?xml version="1.0" encoding="windows-1256" ?>
<formulas>
	<formula c1="Ì" c2="Ð" c3="ã" conjugation="4" adj1="C" adj2="" adj3="">
	</formula>
	<formula c1="Ì" c2="æ" c3="Ú" conjugation="1" adj1="E" adj2="" adj3="">
	</formula>
	<formula c1="Ì" c2="á" c3="á" conjugation="2" adj1="A" adj2="" adj3="">
	</formula>
	<formula c1="Ì" c2="È" c3="å" conjugation="4" adj1="C" adj2="" adj3="">
	</formula>
	<formula c1="Ì" c2="Ë" c3="á" conjugation="5" adj1="D" adj2="" adj3="">
	</formula>
	<formula c1="Ì" c2="Í" c3="ã" conjugation="4" adj1="A" adj2="" adj3="">
	</formula>
	<formula c1="Ì" c2="Ï" c3="È" conjugation="5" adj1="A" adj2="D" adj3="">
	</formula>
	<formula c1="Ì" c2="Ï" c3="Ñ" conjugation="4" adj1="B" adj2="" adj3="">
	</formula>
	<formula c1="Ì" c2="Ï" c3="Ñ" conjugation="5" adj1="A" adj2="" adj3="">
	</formula>
	<formula c1="Ì" c2="Ï" c3="Ú" conjugation="4" adj1="C" adj2="" adj3="">
	</formula>
	<formula c1="Ì" c2="Ï" c3="á" conjugation="4" adj1="B" adj2="" adj3="">
	</formula>
	<formula c1="Ì" c2="Ñ" c3="Á" conjugation="5" adj1="A" adj2="" adj3="">
	</formula>
	<formula c1="Ì" c2="Ñ" c3="È" conjugation="4" adj1="B" adj2="C" adj3="E">
	</formula>
	<formula c1="Ì" c2="Ñ" c3="Ï" conjugation="4" adj1="B" adj2="C" adj3="">
	</formula>
	<formula c1="Ì" c2="Ò" c3="Ú" conjugation="4" adj1="B" adj2="" adj3="">
	</formula>
	<formula c1="Ì" c2="Ò" c3="á" conjugation="5" adj1="A" adj2="D" adj3="">
	</formula>
	<formula c1="Ì" c2="Ó" c3="Ï" conjugation="4" adj1="B" adj2="" adj3="">
	</formula>
	<formula c1="Ì" c2="Ó" c3="ã" conjugation="5" adj1="A" adj2="" adj3="">
	</formula>
	<formula c1="Ì" c2="Ô" c3="Ô" conjugation="4" adj1="C" adj2="" adj3="">
	</formula>
	<formula c1="Ì" c2="Ô" c3="Ú" conjugation="4" adj1="B" adj2="" adj3="">
	</formula>
	<formula c1="Ì" c2="Ú" c3="Ï" conjugation="5" adj1="D" adj2="" adj3="">
	</formula>
	<formula c1="Ì" c2="á" c3="Í" conjugation="4" adj1="C" adj2="" adj3="">
	</formula>
	<formula c1="Ì" c2="á" c3="Ï" conjugation="5" adj1="A" adj2="D" adj3="">
	</formula>
	<formula c1="Ì" c2="á" c3="å" conjugation="4" adj1="C" adj2="" adj3="">
	</formula>
	<formula c1="Ì" c2="ã" c3="á" conjugation="5" adj1="A" adj2="" adj3="">
	</formula>
	<formula c1="Ì" c2="ã" c3="ã" conjugation="4" adj1="C" adj2="" adj3="">
	</formula>
	<formula c1="Ì" c2="ä" c3="Ý" conjugation="4" adj1="C" adj2="" adj3="">
	</formula>
	<formula c1="Ì" c2="å" c3="Ï" conjugation="4" adj1="B" adj2="" adj3="">
	</formula>
	<formula c1="Ì" c2="å" c3="Ñ" conjugation="5" adj1="A" adj2="" adj3="">
	</formula>
	<formula c1="Ì" c2="å" c3="ã" conjugation="5" adj1="A" adj2="D" adj3="">
	</formula>
</formulas>
