<?xml version="1.0" encoding="windows-1256" ?>
<roots>
	<root c1="È" c2="Á" c3="È" c4="Á" transitive="ß">
	</root>
	<root c1="È" c2="Á" c3="Ï" c4="á" transitive="á">
	</root>
	<root c1="È" c2="Á" c3="Ð" c4="ä" transitive="á">
	</root>
	<root c1="È" c2="Ë" c3="È" c4="Ë" transitive="ã">
	</root>
	<root c1="È" c2="Ì" c3="È" c4="Ì" transitive="ß">
	</root>
	<root c1="È" c2="Í" c3="È" c4="Í" transitive="ß">
	</root>
	<root c1="È" c2="Í" c3="Ê" c4="ä" transitive="á">
	</root>
	<root c1="È" c2="Í" c3="Ë" c4="Ñ" transitive="ß">
	</root>
	<root c1="È" c2="Í" c3="Ï" c4="á" transitive="á">
	</root>
	<root c1="È" c2="Í" c3="Ô" c4="á" transitive="á">
	</root>
	<root c1="È" c2="Í" c3="Ù" c4="á" transitive="á">
	</root>
	<root c1="È" c2="Î" c3="È" c4="Î" transitive="ß">
	</root>
	<root c1="È" c2="Î" c3="Ê" c4="Ñ" transitive="á">
	</root>
	<root c1="È" c2="Î" c3="Ë" c4="Ñ" transitive="ã">
	</root>
	<root c1="È" c2="Î" c3="Ð" c4="Ú" transitive="ã">
	</root>
	<root c1="È" c2="Î" c3="Ö" c4="á" transitive="á">
	</root>
	<root c1="È" c2="Î" c3="á" c4="Õ" transitive="á">
	</root>
	<root c1="È" c2="Î" c3="ä" c4="Þ" transitive="ã">
	</root>
	<root c1="È" c2="Ð" c3="È" c4="Ð" transitive="ß">
	</root>
	<root c1="È" c2="Ð" c3="Ñ" c4="Þ" transitive="ß">
	</root>
	<root c1="È" c2="Ð" c3="Þ" c4="Ø" transitive="ã">
	</root>
	<root c1="È" c2="Ð" c3="á" c4="Î" transitive="á">
	</root>
	<root c1="È" c2="Ñ" c3="Á" c4="á" transitive="á">
	</root>
	<root c1="È" c2="Ñ" c3="È" c4="Ñ" transitive="á">
	</root>
	<root c1="È" c2="Ñ" c3="È" c4="Ó" transitive="ã">
	</root>
	<root c1="È" c2="Ñ" c3="È" c4="Õ" transitive="ã">
	</root>
	<root c1="È" c2="Ñ" c3="Ê" c4="ß" transitive="ã">
	</root>
	<root c1="È" c2="Ñ" c3="Ë" c4="Ø" transitive="á">
	</root>
	<root c1="È" c2="Ñ" c3="Ì" c4="ã" transitive="ß">
	</root>
	<root c1="È" c2="Ñ" c3="Ð" c4="ä" transitive="ß">
	</root>
	<root c1="È" c2="Ñ" c3="Ó" c4="ã" transitive="ã">
	</root>
	<root c1="È" c2="Ñ" c3="Ô" c4="Ø" transitive="ã">
	</root>
	<root c1="È" c2="Ñ" c3="Ô" c4="Þ" transitive="ã">
	</root>
	<root c1="È" c2="Ñ" c3="Ô" c4="ß" transitive="ã">
	</root>
	<root c1="È" c2="Ñ" c3="Ô" c4="ã" transitive="ß">
	</root>
	<root c1="È" c2="Ñ" c3="Ø" c4="Ó" transitive="á">
	</root>
	<root c1="È" c2="Ñ" c3="Ø" c4="á" transitive="ß">
	</root>
	<root c1="È" c2="Ñ" c3="Ø" c4="ã" transitive="ß">
	</root>
	<root c1="È" c2="Ñ" c3="Ú" c4="ã" transitive="á">
	</root>
	<root c1="È" c2="Ñ" c3="Û" c4="Ë" transitive="á">
	</root>
	<root c1="È" c2="Ñ" c3="Û" c4="Ô" transitive="á">
	</root>
	<root c1="È" c2="Ñ" c3="Û" c4="á" transitive="á">
	</root>
	<root c1="È" c2="Ñ" c3="Þ" c4="Í" transitive="á">
	</root>
	<root c1="È" c2="Ñ" c3="Þ" c4="Ô" transitive="ß">
	</root>
	<root c1="È" c2="Ñ" c3="Þ" c4="Ø" transitive="ß">
	</root>
	<root c1="È" c2="Ñ" c3="Þ" c4="Ú" transitive="ã">
	</root>
	<root c1="È" c2="Ñ" c3="Þ" c4="á" transitive="á">
	</root>
	<root c1="È" c2="Ñ" c3="ß" c4="Ú" transitive="ß">
	</root>
	<root c1="È" c2="Ñ" c3="ã" c4="Ì" transitive="ã">
	</root>
	<root c1="È" c2="Ñ" c3="ä" c4="Ó" transitive="ã">
	</root>
	<root c1="È" c2="Ñ" c3="ä" c4="Þ" transitive="ã">
	</root>
	<root c1="È" c2="Ñ" c3="å" c4="ã" transitive="á">
	</root>
	<root c1="È" c2="Ñ" c3="å" c4="ä" transitive="ß">
	</root>
	<root c1="È" c2="Ñ" c3="æ" c4="Ò" transitive="ã">
	</root>
	<root c1="È" c2="Ò" c3="È" c4="Ò" transitive="ß">
	</root>
	<root c1="È" c2="Ò" c3="ã" c4="Î" transitive="á">
	</root>
	<root c1="È" c2="Ó" c3="È" c4="Ó" transitive="á">
	</root>
	<root c1="È" c2="Ó" c3="Ê" c4="Ñ" transitive="ã">
	</root>
	<root c1="È" c2="Ó" c3="ã" c4="á" transitive="á">
	</root>
	<root c1="È" c2="Ô" c3="È" c4="Ô" transitive="á">
	</root>
	<root c1="È" c2="Õ" c3="È" c4="Õ" transitive="ß">
	</root>
	<root c1="È" c2="Ö" c3="È" c4="Ö" transitive="ã">
	</root>
	<root c1="È" c2="Ø" c3="È" c4="Ø" transitive="ã">
	</root>
	<root c1="È" c2="Ù" c3="Ñ" c4="ã" transitive="á">
	</root>
	<root c1="È" c2="Ú" c3="È" c4="Ú" transitive="á">
	</root>
	<root c1="È" c2="Ú" c3="Ë" c4="Ñ" transitive="ß">
	</root>
	<root c1="È" c2="Ú" c3="Ð" c4="Ñ" transitive="ã">
	</root>
	<root c1="È" c2="Ú" c3="Ò" c4="Þ" transitive="ã">
	</root>
	<root c1="È" c2="Ú" c3="ß" c4="Ñ" transitive="ã">
	</root>
	<root c1="È" c2="Ú" c3="ä" c4="Ó" transitive="á">
	</root>
	<root c1="È" c2="Û" c3="È" c4="Û" transitive="ã">
	</root>
	<root c1="È" c2="Û" c3="Ë" c4="Ñ" transitive="ß">
	</root>
	<root c1="È" c2="Û" c3="Ó" c4="á" transitive="á">
	</root>
	<root c1="È" c2="Þ" c3="È" c4="Þ" transitive="ß">
	</root>
	<root c1="È" c2="ß" c3="È" c4="ß" transitive="ß">
	</root>
	<root c1="È" c2="á" c3="Á" c4="Ò" transitive="á">
	</root>
	<root c1="È" c2="á" c3="Á" c4="Õ" transitive="á">
	</root>
	<root c1="È" c2="á" c3="È" c4="á" transitive="ã">
	</root>
	<root c1="È" c2="á" c3="Ê" c4="í" transitive="ã">
	</root>
	<root c1="È" c2="á" c3="Ì" c4="ã" transitive="ã">
	</root>
	<root c1="È" c2="á" c3="Í" c4="ã" transitive="ã">
	</root>
	<root c1="È" c2="á" c3="Ï" c4="Í" transitive="á">
	</root>
	<root c1="È" c2="á" c3="Ï" c4="ã" transitive="á">
	</root>
	<root c1="È" c2="á" c3="Ó" c4="ã" transitive="ß">
	</root>
	<root c1="È" c2="á" c3="Õ" c4="ã" transitive="á">
	</root>
	<root c1="È" c2="á" c3="Ø" c4="Í" transitive="ß">
	</root>
	<root c1="È" c2="á" c3="Ø" c4="ã" transitive="á">
	</root>
	<root c1="È" c2="á" c3="Ú" c4="ß" transitive="ã">
	</root>
	<root c1="È" c2="á" c3="Ú" c4="ã" transitive="ã">
	</root>
	<root c1="È" c2="á" c3="Þ" c4="Ú" transitive="á">
	</root>
	<root c1="È" c2="á" c3="ß" c4="Ú" transitive="ã">
	</root>
	<root c1="È" c2="á" c3="å" c4="Ó" transitive="á">
	</root>
	<root c1="È" c2="á" c3="å" c4="Õ" transitive="á">
	</root>
	<root c1="È" c2="á" c3="å" c4="Þ" transitive="á">
	</root>
	<root c1="È" c2="á" c3="æ" c4="Ñ" transitive="ã">
	</root>
	<root c1="È" c2="ä" c3="È" c4="ä" transitive="á">
	</root>
	<root c1="È" c2="ä" c3="Ï" c4="Þ" transitive="ß">
	</root>
	<root c1="È" c2="å" c3="È" c4="å" transitive="á">
	</root>
	<root c1="È" c2="å" c3="Ê" c4="Ñ" transitive="á">
	</root>
	<root c1="È" c2="å" c3="Ï" c4="á" transitive="á">
	</root>
	<root c1="È" c2="å" c3="Ñ" c4="Ì" transitive="ß">
	</root>
	<root c1="È" c2="å" c3="Ñ" c4="ã" transitive="ã">
	</root>
	<root c1="È" c2="å" c3="Õ" c4="á" transitive="ß">
	</root>
	<root c1="È" c2="å" c3="á" c4="Þ" transitive="ß">
	</root>
	<root c1="È" c2="å" c3="ä" c4="Ó" transitive="á">
	</root>
	<root c1="È" c2="í" c3="Ï" c4="Ñ" transitive="ã">
	</root>
	<root c1="È" c2="í" c3="Ø" c4="Ñ" transitive="á">
	</root>
	<root c1="È" c2="í" c3="Þ" c4="Ñ" transitive="á">
	</root>
</roots>
